[
  {
    "id": 0,
    "title": "出差",
    "checkpoints": [
      {
        "title": "身份证",
        "isDone": false
      },
      {
        "title": "衣服",
        "isDone": true
      },
      {
        "title": "会员卡",
        "isDone": false
      },
      {
        "title": "充电器",
        "isDone": true
      }
    ]
  },
  {
    "id": 1,
    "title": "羽毛球",
    "checkpoints": [
      {
        "title": "球拍",
        "isDone": true
      },
      {
        "title": "毛巾",
        "isDone": false
      }
    ]
  }
]
